[
  {
    "entity": "BAC Credomatic",
    "ratesByCurrency": {
      "CRC": {
        "1": [
          {
            "min": 250000,
            "max": 5000000,
            "gross": 4.12,
            "net": 3.5
          },
          {
            "min": 5000001,
            "max": 15000000,
            "gross": 4.29,
            "net": 3.65
          },
          {
            "min": 15000001,
            "max": 100000000,
            "gross": 4.47,
            "net": 3.8
          },
          {
            "min": 100000001,
            "max": 200000000,
            "gross": 4.59,
            "net": 3.9
          },
          {
            "min": 200000001,
            "max": 999999999,
            "gross": 4.59,
            "net": 3.9
          }
        ],
        "3": [
          {
            "min": 250000,
            "max": 5000000,
            "gross": 4.43,
            "net": 3.77
          },
          {
            "min": 5000001,
            "max": 15000000,
            "gross": 4.6,
            "net": 3.91
          },
          {
            "min": 15000001,
            "max": 100000000,
            "gross": 4.78,
            "net": 4.06
          },
          {
            "min": 100000001,
            "max": 200000000,
            "gross": 4.9,
            "net": 4.17
          },
          {
            "min": 200000001,
            "max": 999999999,
            "gross": 4.9,
            "net": 4.17
          }
        ],
        "6": [
          {
            "min": 250000,
            "max": 5000000,
            "gross": 5.04,
            "net": 4.28
          },
          {
            "min": 5000001,
            "max": 15000000,
            "gross": 5.22,
            "net": 4.44
          },
          {
            "min": 15000001,
            "max": 100000000,
            "gross": 5.4,
            "net": 4.59
          },
          {
            "min": 100000001,
            "max": 200000000,
            "gross": 5.52,
            "net": 4.69
          },
          {
            "min": 200000001,
            "max": 999999999,
            "gross": 5.52,
            "net": 4.69
          }
        ],
        "12": [
          {
            "min": 250000,
            "max": 5000000,
            "gross": 5.71,
            "net": 4.85
          },
          {
            "min": 5000001,
            "max": 15000000,
            "gross": 5.89,
            "net": 5.01
          },
          {
            "min": 15000001,
            "max": 100000000,
            "gross": 6.06,
            "net": 5.15
          },
          {
            "min": 100000001,
            "max": 200000000,
            "gross": 6.18,
            "net": 5.25
          },
          {
            "min": 200000001,
            "max": 999999999,
            "gross": 6.18,
            "net": 5.25
          }
        ]
      },
      "USD": {
        "1": [
          {
            "min": 1500,
            "max": 10000,
            "gross": 2.94,
            "net": 2.5
          },
          {
            "min": 10001,
            "max": 25000,
            "gross": 3.12,
            "net": 2.65
          },
          {
            "min": 25001,
            "max": 150000,
            "gross": 3.29,
            "net": 2.8
          },
          {
            "min": 150001,
            "max": 400000,
            "gross": 3.41,
            "net": 2.9
          },
          {
            "min": 400001,
            "max": 999999999,
            "gross": 3.41,
            "net": 2.9
          }
        ],
        "3": [
          {
            "min": 1500,
            "max": 10000,
            "gross": 3.24,
            "net": 2.75
          },
          {
            "min": 10001,
            "max": 25000,
            "gross": 3.42,
            "net": 2.91
          },
          {
            "min": 25001,
            "max": 150000,
            "gross": 3.6,
            "net": 3.06
          },
          {
            "min": 150001,
            "max": 400000,
            "gross": 3.71,
            "net": 3.15
          },
          {
            "min": 400001,
            "max": 999999999,
            "gross": 3.71,
            "net": 3.15
          }
        ],
        "6": [
          {
            "min": 1500,
            "max": 10000,
            "gross": 3.85,
            "net": 3.27
          },
          {
            "min": 10001,
            "max": 25000,
            "gross": 4.03,
            "net": 3.43
          },
          {
            "min": 25001,
            "max": 150000,
            "gross": 4.2,
            "net": 3.57
          },
          {
            "min": 150001,
            "max": 400000,
            "gross": 4.32,
            "net": 3.67
          },
          {
            "min": 400001,
            "max": 999999999,
            "gross": 4.32,
            "net": 3.67
          }
        ],
        "12": [
          {
            "min": 1500,
            "max": 10000,
            "gross": 4.79,
            "net": 4.07
          },
          {
            "min": 10001,
            "max": 25000,
            "gross": 4.97,
            "net": 4.22
          },
          {
            "min": 25001,
            "max": 150000,
            "gross": 5.15,
            "net": 4.38
          },
          {
            "min": 150001,
            "max": 400000,
            "gross": 5.26,
            "net": 4.47
          },
          {
            "min": 400001,
            "max": 999999999,
            "gross": 5.26,
            "net": 4.47
          }
        ]
      }
    }
  },
  {
    "entity": "Banco de Costa Rica",
    "ratesByCurrency": {
      "CRC": {
        "1": [
          {
            "min": 50000,
            "max": null,
            "gross": 2.96,
            "net": 2.52
          }
        ],
        "3": [
          {
            "min": 50000,
            "max": null,
            "gross": 3.77,
            "net": 3.2
          }
        ],
        "6": [
          {
            "min": 50000,
            "max": null,
            "gross": 4.68,
            "net": 3.98
          }
        ],
        "12": [
          {
            "min": 50000,
            "max": null,
            "gross": 5.4,
            "net": 4.59
          }
        ]
      },
      "USD": {
        "1": [
          {
            "min": 100,
            "max": null,
            "gross": 1.66,
            "net": 1.41
          }
        ],
        "3": [
          {
            "min": 100,
            "max": null,
            "gross": 2.01,
            "net": 1.71
          }
        ],
        "6": [
          {
            "min": 100,
            "max": null,
            "gross": 2.86,
            "net": 2.43
          }
        ],
        "12": [
          {
            "min": 100,
            "max": null,
            "gross": 3.83,
            "net": 3.26
          }
        ]
      }
    }
  },
  {
    "entity": "Banco Nacional",
    "ratesByCurrency": {
      "CRC": {
        "1": [
          {
            "min": 50000,
            "max": null,
            "gross": 2.99,
            "net": 2.54
          }
        ],
        "3": [
          {
            "min": 50000,
            "max": null,
            "gross": 3.7,
            "net": 3.15
          }
        ],
        "6": [
          {
            "min": 50000,
            "max": null,
            "gross": 4.7,
            "net": 4
          }
        ],
        "12": [
          {
            "min": 50000,
            "max": null,
            "gross": 5.34,
            "net": 4.54
          }
        ]
      },
      "USD": {
        "1": [
          {
            "min": 100,
            "max": null,
            "gross": 1.34,
            "net": 1.14
          }
        ],
        "3": [
          {
            "min": 100,
            "max": null,
            "gross": 1.7,
            "net": 1.44
          }
        ],
        "6": [
          {
            "min": 100,
            "max": null,
            "gross": 2.52,
            "net": 2.14
          }
        ],
        "12": [
          {
            "min": 100,
            "max": null,
            "gross": 3.76,
            "net": 3.2
          }
        ]
      }
    }
  },
  {
    "entity": "Banco Popular",
    "ratesByCurrency": {
      "CRC": {
        "1": [
          {
            "min": 0,
            "max": null,
            "gross": 2.95,
            "net": 2.6
          }
        ],
        "3": [
          {
            "min": 0,
            "max": null,
            "gross": 3.75,
            "net": 3.3
          }
        ],
        "6": [
          {
            "min": 0,
            "max": null,
            "gross": 4.75,
            "net": 4.18
          }
        ],
        "12": [
          {
            "min": 0,
            "max": null,
            "gross": 5.35,
            "net": 4.71
          }
        ]
      },
      "USD": {
        "1": [
          {
            "min": 0,
            "max": null,
            "gross": 1.60,
            "net": 1.41
          }
        ],
        "3": [
          {
            "min": 0,
            "max": null,
            "gross": 2.1,
            "net": 1.85
          }
        ],
        "6": [
          {
            "min": 0,
            "max": null,
            "gross": 3.85,
            "net": 3.39
          }
        ],
        "12": [
          {
            "min": 0,
            "max": null,
            "gross": 4.45,
            "net": 3.92
          }
        ]
      }
    }
  },
  {
    "entity": "Scotiabank",
    "ratesByCurrency": {
      "CRC": {
        "1": [],
        "3": [],
        "6": [],
        "12": []
      },
      "USD": {
        "1": [
          {
            "min": 1500,
            "max": 1500,
            "gross": 3,
            "net": 2.55
          }
        ],
        "3": [
          {
            "min": 1500,
            "max": 1500,
            "gross": 3.2941,
            "net": 2.8
          }
        ],
        "6": [
          {
            "min": 1500,
            "max": 1500,
            "gross": 3.9412,
            "net": 3.35
          }
        ],
        "12": [
          {
            "min": 1500,
            "max": 1500,
            "gross": 4.8824,
            "net": 4.15
          }
        ]
      }
    }
  }
]